{
  "workload_id": 4,
  "query_ids": [
    "sf10_job_14a",
    "sf10_job_22a",
    "sf10_job_23a",
    "sf10_job_26a",
    "sf10_job_28a",
    "sf10_job_33a",
    "sf10_job_4c"
  ],
  "combo": "trino/iceberg",
  "conf": "memory.heap-headroom-per-node=16; node-scheduler.max-splits-per-node=200; query.max-memory=28; query.max-memory-per-node=16; query.max-total-memory-per-node=12; task.concurrency=12; task.max-worker-threads=24",
  "assignments": {
    "sf10_job_28a": {
      "combo": "trino/iceberg",
      "latency": 3177.56,
      "optimal_latency": 1543.92,
      "query_ratio": 2.0581
    },
    "sf10_job_23a": {
      "combo": "trino/iceberg",
      "latency": 4254.56,
      "optimal_latency": 1587.91,
      "query_ratio": 2.6793
    },
    "sf10_job_26a": {
      "combo": "trino/iceberg",
      "latency": 3618.59,
      "optimal_latency": 1698.84,
      "query_ratio": 2.13
    },
    "sf10_job_22a": {
      "combo": "trino/iceberg",
      "latency": 3645.71,
      "optimal_latency": 1677.15,
      "query_ratio": 2.1738
    },
    "sf10_job_4c": {
      "combo": "trino/iceberg",
      "latency": 3227.78,
      "optimal_latency": 1505.0,
      "query_ratio": 2.1447
    },
    "sf10_job_14a": {
      "combo": "trino/iceberg",
      "latency": 3712.86,
      "optimal_latency": 1501.57,
      "query_ratio": 2.4727
    },
    "sf10_job_33a": {
      "combo": "trino/iceberg",
      "latency": 3104.31,
      "optimal_latency": 1620.32,
      "query_ratio": 1.9159
    }
  },
  "total_latency": 24741.37,
  "optimal_total": 11134.71,
  "actual_ratio": 2.222,
  "target_ratio": 2.26
}