{
  "workload_id": 32,
  "query_ids": [
    "sf10_db13",
    "sf10_db18",
    "sf10_db4",
    "sf10_q11",
    "sf10_q14"
  ],
  "combo": "trino/iceberg",
  "conf": "memory.heap-headroom-per-node=16; node-scheduler.max-splits-per-node=200; query.max-memory=28; query.max-memory-per-node=16; query.max-total-memory-per-node=12; task.concurrency=12; task.max-worker-threads=24",
  "assignments": {
    "sf10_db4": {
      "combo": "trino/iceberg",
      "latency": 4629.15,
      "optimal_latency": 2109.0,
      "query_ratio": 2.195
    },
    "sf10_q11": {
      "combo": "trino/iceberg",
      "latency": 2748.91,
      "optimal_latency": 1500.06,
      "query_ratio": 1.8325
    },
    "sf10_db18": {
      "combo": "trino/iceberg",
      "latency": 3356.89,
      "optimal_latency": 1546.16,
      "query_ratio": 2.1711
    },
    "sf10_q14": {
      "combo": "trino/iceberg",
      "latency": 3235.85,
      "optimal_latency": 1500.3,
      "query_ratio": 2.1568
    },
    "sf10_db13": {
      "combo": "trino/iceberg",
      "latency": 6346.6,
      "optimal_latency": 3397.02,
      "query_ratio": 1.8683
    }
  },
  "total_latency": 20317.4,
  "optimal_total": 10052.54,
  "actual_ratio": 2.0211,
  "target_ratio": 1.91
}