{
  "workload_id": 6,
  "query_ids": [
    "sf1_query13",
    "sf1_query15",
    "sf1_query23_a",
    "sf1_query26",
    "sf1_query56",
    "sf1_query6",
    "sf1_query66",
    "sf1_query70",
    "sf1_query73",
    "sf1_query84",
    "sf1_query88",
    "sf1_query97"
  ],
  "combo": "trino/iceberg",
  "conf": "memory.heap-headroom-per-node=16; node-scheduler.max-splits-per-node=200; query.max-memory=28; query.max-memory-per-node=16; query.max-total-memory-per-node=12; task.concurrency=12; task.max-worker-threads=24",
  "assignments": {
    "sf1_query97": {
      "combo": "trino/iceberg",
      "latency": 2366.0,
      "optimal_latency": 1602.0,
      "query_ratio": 1.4769
    },
    "sf1_query23_a": {
      "combo": "trino/iceberg",
      "latency": 2406.31,
      "optimal_latency": 2084.96,
      "query_ratio": 1.1541
    },
    "sf1_query73": {
      "combo": "trino/iceberg",
      "latency": 1725.54,
      "optimal_latency": 1500.47,
      "query_ratio": 1.15
    },
    "sf1_query15": {
      "combo": "trino/iceberg",
      "latency": 2185.26,
      "optimal_latency": 1516.81,
      "query_ratio": 1.4407
    },
    "sf1_query66": {
      "combo": "trino/iceberg",
      "latency": 2265.78,
      "optimal_latency": 1500.47,
      "query_ratio": 1.51
    },
    "sf1_query13": {
      "combo": "trino/iceberg",
      "latency": 1803.41,
      "optimal_latency": 1501.0,
      "query_ratio": 1.2015
    },
    "sf1_query6": {
      "combo": "trino/iceberg",
      "latency": 2064.36,
      "optimal_latency": 1500.47,
      "query_ratio": 1.3758
    },
    "sf1_query84": {
      "combo": "trino/iceberg",
      "latency": 2228.23,
      "optimal_latency": 1548.41,
      "query_ratio": 1.439
    },
    "sf1_query26": {
      "combo": "trino/iceberg",
      "latency": 1889.41,
      "optimal_latency": 1584.18,
      "query_ratio": 1.1927
    },
    "sf1_query70": {
      "combo": "trino/iceberg",
      "latency": 2256.36,
      "optimal_latency": 1500.47,
      "query_ratio": 1.5038
    },
    "sf1_query56": {
      "combo": "trino/iceberg",
      "latency": 2194.2,
      "optimal_latency": 1500.47,
      "query_ratio": 1.4623
    },
    "sf1_query88": {
      "combo": "trino/iceberg",
      "latency": 2081.92,
      "optimal_latency": 1523.02,
      "query_ratio": 1.367
    }
  },
  "total_latency": 25466.78,
  "optimal_total": 18862.72,
  "actual_ratio": 1.3501,
  "target_ratio": 1.35
}